rtl/alu_opcodes.vh
`define ALU_ADD   5'b00000
`define ALU_SUB   5'b00001
`define ALU_AND   5'b00010
`define ALU_OR    5'b00011
`define ALU_XOR   5'b00100
`define ALU_NOR   5'b00101
`define ALU_SLL   5'b00110
`define ALU_SRL   5'b00111
`define ALU_SRA   5'b01000
`define ALU_SLT   5'b01001
`define ALU_SLTU  5'b01010
`define ALU_EQ    5'b01011
`define ALU_NEQ   5'b01100
`define ALU_GT    5'b01101
`define ALU_LT    5'b01110
`define ALU_PASS  5'b01111

rtl/alu32.v
`include "alu_opcodes.vh"  
// Includes the file with opcode macro definitions (e.g., `ALU_ADD`, `ALU_SUB`, etc.)
// The backtick ` is the Verilog preprocessor directive symbol, similar to #include in C/C++.

module alu32 (
    input  logic [31:0] a,            // 32-bit input operand A
    input  logic [31:0] b,            // 32-bit input operand B
    input  logic [4:0]  opcode,       // 5-bit operation code that selects ALU operation (up to 32 ops)
    output logic [31:0] result,       // 32-bit result of the operation
    output logic        zero,         // Flag: result is zero
    output logic        negative,     // Flag: result is negative (MSB = 1)
    output logic        carry_out,    // Flag: carry out from addition or subtraction
    output logic        overflow      // Flag: signed overflow in addition/subtraction
);
// `logic` is used instead of `wire` to allow assignment in procedural blocks (e.g., always_comb)

    logic [31:0] sum;                 // Temporary variable to store result of addition
    logic [31:0] diff;                // Temporary variable to store result of subtraction
    logic        carry_add;           // Carry-out from addition
    logic        carry_sub;           // Carry-out from subtraction

    assign {carry_add, sum}  = a + b;
// Performs 32-bit addition. The result is 33 bits: upper bit (carry_out) is assigned to carry_add,
// and lower 32 bits are assigned to sum.
// Curly braces `{}` are used to concatenate values. So `{carry_add, sum}` means pack into a 33-bit value.

    assign {carry_sub, diff} = a - b;
// Same as above, but for subtraction. Note: carry_sub behaves like borrow flag.

    always_comb begin
// `always_comb` is synthesizable and triggers whenever any input in the block changes.
// It ensures purely combinational logic, replacing `always @(*)` in SystemVerilog.

        result     = 32'b0;           // Initialize result to all 0s. '32'b0' = 32-bit binary zero
        carry_out  = 1'b0;            // Initialize carry_out to 0. '1'b0' = 1-bit binary zero
        overflow   = 1'b0;            // Initialize overflow flag

        case (opcode)
        // Begin a case statement to select the operation based on the 5-bit opcode

            `ALU_ADD:   begin result = sum;       carry_out = carry_add; end
            // Add: Assign precomputed sum, set carry_out from addition

            `ALU_SUB:   begin result = diff;      carry_out = carry_sub; end
            // Subtract: Assign precomputed difference, set carry_out from subtraction

            `ALU_AND:   result = a & b;
            // Bitwise AND: Each bit of result = a[i] AND b[i]

            `ALU_OR:    result = a | b;
            // Bitwise OR: Each bit of result = a[i] OR b[i]

            `ALU_XOR:   result = a ^ b;
            // Bitwise XOR: Each bit of result = a[i] XOR b[i]

            `ALU_NOR:   result = ~(a | b);
            // Bitwise NOR: First compute OR, then bitwise NOT

            `ALU_SLL:   result = a << b[4:0];
            // Logical Shift Left: shift `a` left by amount in b[4:0]
            // `<<` shifts bits to the left, padding with zeros on the right

            `ALU_SRL:   result = a >> b[4:0];
            // Logical Shift Right: shift `a` right by b[4:0] (zero-fill)
            // `>>` shifts bits right, padding with zeros on the left

            `ALU_SRA:   result = $signed(a) >>> b[4:0];
            // Arithmetic Shift Right: sign-extend the shifted bits
            // `>>>` is arithmetic right shift operator (preserves sign)
            // `$signed()` casts a to a signed number before shifting

            `ALU_SLT:   result = ($signed(a) < $signed(b)) ? 32'd1 : 32'd0;
            // Set Less Than (signed): If a < b, result = 1 else 0
            // `? :` is the ternary operator: condition ? true_value : false_value
            // `32'd1` means 32-bit decimal 1

            `ALU_SLTU:  result = (a < b) ? 32'd1 : 32'd0;
            // Set Less Than Unsigned: compares `a` and `b` as unsigned numbers

            `ALU_EQ:    result = (a == b) ? 32'd1 : 32'd0;
            // Equality check: If a == b, result = 1 else 0

            `ALU_NEQ:   result = (a != b) ? 32'd1 : 32'd0;
            // Not equal check

            `ALU_GT:    result = ($signed(a) > $signed(b)) ? 32'd1 : 32'd0;
            // Greater than (signed)

            `ALU_LT:    result = ($signed(a) < $signed(b)) ? 32'd1 : 32'd0;
            // Less than (signed) — similar to `ALU_SLT`

            `ALU_PASS:  result = a;
            // Pass-through: return operand `a` unchanged

            default:    result = 32'bx;
            // If opcode doesn't match any case, result is undefined (all x)

        endcase

        zero     = (result == 32'b0);
        // Set zero flag if result is all zeros

        negative = result[31];
        // Set negative flag based on MSB of result (sign bit in 2's complement)

        overflow = (opcode == `ALU_ADD) ? ((a[31] == b[31]) && (result[31] != a[31])) :
                   (opcode == `ALU_SUB) ? ((a[31] != b[31]) && (result[31] != a[31])) : 1'b0;
        // Overflow flag logic:
        // For addition: overflow if inputs had same sign but result has different sign
        // For subtraction: overflow if inputs had opposite sign and result sign mismatches with a
        // Otherwise, overflow is zero
    end

endmodule





// Aha! Moment #1: Carry-out captured with concatenation
// Verilog allows us to pack the carry-out and result together like this:
// {carry_out, sum} = a + b; ensures we don't lose the 33rd bit of the addition
//assign {carry_add, sum} = a + b;

// Aha! Moment #2: Overflow and carry-out are different!
// Carry-out is for unsigned numbers, overflow is for signed ones (like when adding 2 large positives gives a negative)
//assign overflow = (a[31] == b[31]) && (sum[31] != a[31]);

// Aha! Moment #3: Signed arithmetic uses the MSB as a sign bit
// So when we detect overflow, we must compare MSBs to see if the result "flipped signs"
//assign signed_overflow = (a[31] == b[31]) && (result[31] != a[31]);

// Aha! Moment #4: Concatenation isn't just syntax—it’s needed to pack carry and result
// It ensures nothing gets lost when results are wider than 32 bits

// Aha! Moment #5: Why 32-bit ALU?
// Because many CPUs use 32-bit registers and instructions, so the ALU must support that width

// Aha! Moment #6: ALU outputs drive CPU decisions
// Zero and carry_out flags are used by CPUs for branching, flag registers, etc.

//assign zero = (result == 32'b0); // Aha! Moment #7: Zero flag helps CPU know if a == b, or if result is zero

// Aha! Moment #8: Opcode controls ALU operation
// Just like instruction decoders, the opcode selects whether we add, subtract, AND, etc.
//always_comb begin
//    case (opcode)
//        5'b00000: result = a + b;       // ADD
//        5'b00001: result = a - b;       // SUB
//        5'b00010: result = a & b;       // AND
//        // ...
//    endcase
//end

// Aha! Moment #9: Bit shifts explained
// Right shifting (a >> b[4:0]) moves bits right and pads with zeros
// Left shifting (a << b[4:0]) moves bits left and introduces zeros on the right

// Aha! Moment #10: Signed arithmetic needs $signed
// To correctly perform arithmetic shifts or comparisons, we must cast operands as signed
//assign signed_less = ($signed(a) < $signed(b)); // compares using two's complement rules

sim/dump.vcd
$version Generated by VerilatedVcd $end
$timescale 1ps $end
 $scope module TOP $end
  $var wire 32 # a [31:0] $end
  $var wire 32 $ b [31:0] $end
  $var wire 5 % opcode [4:0] $end
  $var wire 32 & result [31:0] $end
  $var wire 1 ' zero $end
  $var wire 1 ( negative $end
  $var wire 1 ) carry_out $end
  $var wire 1 * overflow $end
  $scope module alu32 $end
   $var wire 32 # a [31:0] $end
   $var wire 32 $ b [31:0] $end
   $var wire 5 % opcode [4:0] $end
   $var wire 32 & result [31:0] $end
   $var wire 1 ' zero $end
   $var wire 1 ( negative $end
   $var wire 1 ) carry_out $end
   $var wire 1 * overflow $end
   $var wire 32 + sum [31:0] $end
   $var wire 32 , diff [31:0] $end
   $var wire 1 - carry_add $end
   $var wire 1 . carry_sub $end
  $upscope $end
 $upscope $end
$enddefinitions $end


#0
b00000000000000000000000000001010 #
b00000000000000000000000000010100 $
b00000 %
b00000000000000000000000000011110 &
0'
0(
0)
0*
b00000000000000000000000000011110 +
b11111111111111111111111111110110 ,
0-
1.
#1000000
b00000000000000000000000000011110 #
b00000000000000000000000000001010 $
b00001 %
b00000000000000000000000000010100 &
b00000000000000000000000000101000 +
b00000000000000000000000000010100 ,
0.
#2000000
b00000000000000001111111111111111 #
b00000000000000001111000011110000 $
b00010 %
b00000000000000001111000011110000 &
b00000000000000011111000011101111 +
b00000000000000000000111100001111 ,
#3000000
b00000000000000001010101010101010 #
b00000000000000000101010101010101 $
b00011 %
b00000000000000001111111111111111 &
b00000000000000001111111111111111 +
b00000000000000000101010101010101 ,
#4000000
b00100 %
#5000000
b11111111111111111111111111111111 #
b11111111111111111111111111111111 $
b00101 %
b00000000000000000000000000000000 &
1'
b11111111111111111111111111111110 +
b00000000000000000000000000000000 ,
1-
#6000000
b00000000000000000000000000010000 #
b00000000000000000000000000000010 $
b00110 %
b00000000000000000000000001000000 &
0'
b00000000000000000000000000010010 +
b00000000000000000000000000001110 ,
0-
#7000000
b00000000000000000000000010000000 #
b00000000000000000000000000000100 $
b00111 %
b00000000000000000000000000001000 &
b00000000000000000000000010000100 +
b00000000000000000000000001111100 ,
#8000000
b11111111111111111111111111110000 #
b01000 %
b11111111111111111111111111111111 &
1(
b11111111111111111111111111110100 +
b11111111111111111111111111101100 ,
#9000000
b00000000000000000000000000000001 #
b00000000000000000000000000000001 $
b00000 %
b00000000000000000000000000000010 &
0(
b00000000000000000000000000000010 +
b00000000000000000000000000000000 ,
#10000000
b11111111111111111111111111111111 #
b00000000000000000000000000000000 &
1'
1)
b00000000000000000000000000000000 +
b11111111111111111111111111111110 ,
1-
#11000000
b00000000000000000000000000010000 #
b00000000000000000000000000100000 $
b00001 %
b11111111111111111111111111110000 &
0'
1(
b00000000000000000000000000110000 +
b11111111111111111111111111110000 ,
0-
1.
#12000000
b10000000000000000000000000000000 #
b00000000000000000000000000000001 $
b01111111111111111111111111111111 &
0(
0)
1*
b10000000000000000000000000000001 +
b01111111111111111111111111111111 ,
0.
